mwedittypes/__init__.py
mwedittypes/constants.py
mwedittypes/mwedittypes.py
mwedittypes/node_differ.py
mwedittypes/simple_differ.py
mwedittypes/tokenizer.py
mwedittypes/tree_differ.py
mwedittypes/utils.py
mwedittypes-2.1.1.dist-info/LICENSE
mwedittypes-2.1.1.dist-info/METADATA
mwedittypes-2.1.1.dist-info/WHEEL
mwedittypes-2.1.1.dist-info/top_level.txt
mwedittypes-2.1.1.dist-info/RECORD
