Metadata-Version: 2.1
Name: mwedittypes
Version: 2.1.1
Summary: Edit diffs and type detection for Wikipedia
Home-page: https://github.com/geohci/edit-types
Author: geohci & Amamgbu (Isaac Johnson & Jesse Amamgbu)
Author-email: <amamgbujesse@yahoo.com>
License: MIT License
Keywords: python,wikipedia,edit types,edit diffs,wiki,edit detection
Classifier: Development Status :: 4 - Beta
Classifier: License :: OSI Approved :: MIT License
Classifier: Natural Language :: English
Classifier: Programming Language :: Python :: 3
Classifier: Programming Language :: Python :: 3.7
Classifier: Programming Language :: Python :: 3.8
Classifier: Programming Language :: Python :: 3.9
Classifier: Programming Language :: Python :: 3.10
Classifier: Operating System :: Unix
Classifier: Operating System :: MacOS :: MacOS X
Classifier: Operating System :: Microsoft :: Windows
License-File: LICENSE
Requires-Dist: mwparserfromhell
Requires-Dist: anytree
Requires-Dist: mwconstants
Provides-Extra: dev
Requires-Dist: pytest (>=6.2.5) ; extra == 'dev'
Provides-Extra: tests
Requires-Dist: pytest (>=6.2.5) ; extra == 'tests'
